trame_mnist/__init__.py
trame_mnist/app/__init__.py
trame_mnist/app/jupyter.py
trame_mnist/app/main.py
trame_mnist/app/ui.py
trame_mnist/app/engine/__init__.py
trame_mnist/app/engine/charts.py
trame_mnist/app/engine/main.py
trame_mnist/app/engine/ml/__init__.py
trame_mnist/app/engine/ml/common.py
trame_mnist/app/engine/ml/prediction.py
trame_mnist/app/engine/ml/testing.py
trame_mnist/app/engine/ml/training.py
trame_mnist/app/engine/ml/xai.py
trame_mnist-2.1.0.dist-info/LICENSE
trame_mnist-2.1.0.dist-info/METADATA
trame_mnist-2.1.0.dist-info/WHEEL
trame_mnist-2.1.0.dist-info/entry_points.txt
trame_mnist-2.1.0.dist-info/top_level.txt
trame_mnist-2.1.0.dist-info/RECORD
