Metadata-Version: 2.1
Name: trame-mnist
Version: 2.1.0
Summary: Visualization exploration for AI/XAI
Home-page: UNKNOWN
Author: Kitware Inc.
License: BSD License
Keywords: Python,Interactive,Web,Application,Framework
Platform: UNKNOWN
Classifier: Development Status :: 5 - Production/Stable
Classifier: Environment :: Web Environment
Classifier: License :: OSI Approved :: BSD License
Classifier: Natural Language :: English
Classifier: Operating System :: OS Independent
Classifier: Programming Language :: Python :: 3 :: Only
Classifier: Programming Language :: JavaScript
Classifier: Topic :: Software Development :: Libraries :: Application Frameworks
Classifier: Topic :: Software Development :: Libraries :: Python Modules
License-File: LICENSE
Requires-Dist: trame (>=2.1.0)
Requires-Dist: plotly (==5.15.0)
Requires-Dist: pandas
Requires-Dist: torch (==1.10.0)
Requires-Dist: torchvision (==0.11.1)
Requires-Dist: smqtk-classifier (==0.19.0)
Requires-Dist: smqtk-core (==0.19.0)
Requires-Dist: smqtk-dataprovider (==0.18.0)
Requires-Dist: smqtk-descriptors (==0.19.0)
Requires-Dist: smqtk-image-io (==0.17.1)
Requires-Dist: xaitk-saliency (==0.7.0)
Requires-Dist: scikit-learn (==1.3.0)
Requires-Dist: scikit-image (==0.21.0)
